dm_core/__init__.py
dm_core/rabbit/__init__.py
dm_core/rabbit/admin.py
dm_core/rabbit/apps.py
dm_core/rabbit/models.py
dm_core/rabbit/service.py
dm_core/rabbit/utils.py
dm_core/rabbit/tests/__init__.py
dm_core_rabbit-1.0.1.dist-info/licenses/LICENSE
dm_core_rabbit-1.0.1.dist-info/METADATA
dm_core_rabbit-1.0.1.dist-info/WHEEL
dm_core_rabbit-1.0.1.dist-info/top_level.txt
dm_core_rabbit-1.0.1.dist-info/RECORD
