Metadata-Version: 2.4
Name: dm-core-rabbit
Version: 1.0.1
Summary: DM Core Rabbit
Author-email: Romaan Khadeer <romaan@dollarmates.com>
Project-URL: Homepage, https://www.dollarmates.com
Project-URL: Source, https://github.com:dollarmates/dm-libs.git
Classifier: Programming Language :: Python :: 3.10
Classifier: Framework :: Django
Classifier: Operating System :: OS Independent
Classifier: Environment :: Web Environment
Requires-Python: ==3.12.*
License-File: LICENSE
Requires-Dist: pika==1.3.2
Requires-Dist: pika-stubs==0.1.3
Requires-Dist: dm-core-meta
Dynamic: license-file
